{"value":[{"title":"CH1 Mm: Nr. 4 auf dem AB machen","dueDateTime":{"dateTime":"2024-01-16T00:00:00.0000000","timeZone":"UTC"}},{"title":"MA2 Ru: Arbeitsblatt 10 (Iserv) machen.","dueDateTime":{"dateTime":"2024-01-17T00:00:00.0000000","timeZone":"UTC"}},{"title":"de2 Bl: Der ewige Spießer lesen bis Zeugnisferien (Opfer) (Hurensohn) (Homofotze)","dueDateTime":{"dateTime":"2024-01-31T00:00:00.0000000","timeZone":"UTC"}},{"title":"SF5 Wh: Wo wurde in der Schule Design technisch Sachen entschieden und sammeln (Fotos), Fotos von der Schule für ein Moodboard","dueDateTime":{"dateTime":"2024-01-15T00:00:00.0000000","timeZone":"UTC"}},{"title":"de2 Bl: Buch Seite 162 oder so Tabelle ausfüllen + Playmobiel Zusammenfassung IServ","dueDateTime":{"dateTime":"2024-01-17T00:00:00.0000000","timeZone":"UTC"}},{"title":"ge1 Bk: S. 84, M9: Nr.1","dueDateTime":{"dateTime":"2024-01-16T00:00:00.0000000","timeZone":"UTC"}},{"title":"pw2 Wm: Buch Seite 142 Nr. 1 + 2","dueDateTime":{"dateTime":"2024-01-17T00:00:00.0000000","timeZone":"UTC"}},{"title":"en1 Hp: Analyse the traits of character of any one character from the movie","dueDateTime":{"dateTime":"2024-01-17T00:00:00.0000000","timeZone":"UTC"}},{"title":"MA1 Rt: Buch Seite 130 Nr.10","dueDateTime":{"dateTime":"2024-01-16T00:00:00.0000000","timeZone":"UTC"}}]}